setup.py
ethan/__init__.py
ethan/ethan.py
ethan.egg-info/PKG-INFO
ethan.egg-info/SOURCES.txt
ethan.egg-info/dependency_links.txt
ethan.egg-info/not-zip-safe
ethan.egg-info/top_level.txt