Metadata-Version: 2.1
Name: ethan
Version: 0.1
Summary: Ethan Programming
Author: Ethan
Author-email: ethan@gmail.com
Classifier: Programming Language :: Python :: 3
Classifier: Operating System :: OS Independent
Classifier: License :: OSI Approved :: MIT License
